examples/example.py
examples/flask_example.py
spewer/__init__.py
spewer/config.py
spewer/spewer.py
spewer/trace.py
spewer-0.1.2.dist-info/licenses/LICENSE
tests/__init__.py
tests/test_spewer.py
spewer-0.1.2.dist-info/METADATA
spewer-0.1.2.dist-info/WHEEL
spewer-0.1.2.dist-info/top_level.txt
spewer-0.1.2.dist-info/RECORD
