Metadata-Version: 2.4
Name: spewer
Version: 0.1.2
Summary: A Python debugging library for detailed code execution tracing
Author-email: Prince Roshan <princekrroshan01@gmail.com>
Maintainer-email: Prince Roshan <princekrroshan01@gmail.com>
License-Expression: MIT
Project-URL: Homepage, https://github.com/Agent-Hellboy/spewer
Project-URL: Documentation, https://github.com/Agent-Hellboy/spewer#readme
Project-URL: Repository, https://github.com/Agent-Hellboy/spewer
Project-URL: Bug Tracker, https://github.com/Agent-Hellboy/spewer/issues
Keywords: debugging,tracing,development,debug,trace
Classifier: Development Status :: 4 - Beta
Classifier: Intended Audience :: Developers
Classifier: Operating System :: OS Independent
Classifier: Programming Language :: Python :: 3
Classifier: Programming Language :: Python :: 3.9
Classifier: Programming Language :: Python :: 3.10
Classifier: Programming Language :: Python :: 3.11
Classifier: Programming Language :: Python :: 3.12
Classifier: Programming Language :: Python :: 3.13
Classifier: Programming Language :: Python :: 3.14
Classifier: Topic :: Software Development :: Debuggers
Classifier: Topic :: Software Development :: Libraries :: Python Modules
Requires-Python: >=3.9
License-File: LICENSE
Provides-Extra: dev
Requires-Dist: pytest>=6.0; extra == "dev"
Requires-Dist: pytest-cov>=2.0; extra == "dev"
Requires-Dist: ruff>=0.12.7; extra == "dev"
Requires-Dist: pre-commit>=3.0.0; extra == "dev"
Dynamic: license-file
